soliket/__init__.py
soliket/_version.py
soliket/constants.py
soliket/utils.py
soliket/bias/Bias.yaml
soliket/bias/Linear_bias.yaml
soliket/bias/__init__.py
soliket/bias/bias.py
soliket/cash/__init__.py
soliket/cash/cash.py
soliket/cash/cash_data.py
soliket/ccl/CCL.yaml
soliket/ccl/__init__.py
soliket/ccl/ccl.py
soliket/ccl_tracers/CCLTracersCrossLikelihood.yaml
soliket/ccl_tracers/GalaxyKappaLikelihood.yaml
soliket/ccl_tracers/ShearKappaLikelihood.yaml
soliket/ccl_tracers/__init__.py
soliket/ccl_tracers/ccl_tracers.py
soliket/clusters/__init__.py
soliket/clusters/clusters.py
soliket/clusters/massfunc.py
soliket/clusters/survey.py
soliket/clusters/sz_utils.py
soliket/clusters/tinker.py
soliket/clusters/data/ACTPol_Cond_scatv5.fits
soliket/clusters/data/E-D56Clusters.fits
soliket/clusters/data/selFn_equD56/QFit.fits
soliket/clusters/data/selFn_equD56/RMSMap_Arnaud_M2e14_z0p4.fits.gz
soliket/clusters/data/selFn_equD56/RMSTab.fits
soliket/clusters/data/selFn_equD56/areaMask.fits.gz
soliket/clusters/data/selFn_equD56/fRelWeights.fits
soliket/cosmopower/CosmoPower.yaml
soliket/cosmopower/CosmoPowerDerived.yaml
soliket/cosmopower/__init__.py
soliket/cosmopower/cosmopower.py
soliket/cosmopower/data/CP_paper/cmb_EE_NN.pkl
soliket/cosmopower/data/CP_paper/cmb_TE_PCAplusNN.pkl
soliket/cosmopower/data/CP_paper/cmb_TT_NN.pkl
soliket/gaussian/__init__.py
soliket/gaussian/gaussian.py
soliket/gaussian/gaussian_data.py
soliket/halo_model/HaloModel.yaml
soliket/halo_model/HaloModel_pyhm.yaml
soliket/halo_model/__init__.py
soliket/halo_model/halo_model.py
soliket/lensing/__init__.py
soliket/lensing/lensing.py
soliket/lensing/data/lensing.sacc.fits
soliket/poisson/__init__.py
soliket/poisson/poisson.py
soliket/poisson/poisson_data.py
soliket/xcorr/XcorrLikelihood.yaml
soliket/xcorr/__init__.py
soliket/xcorr/limber.py
soliket/xcorr/xcorr.py
soliket/xcorr/data/clgg.txt
soliket/xcorr/data/clkg.txt
soliket/xcorr/data/dndz.txt
soliket-0.3.1.dist-info/METADATA
soliket-0.3.1.dist-info/WHEEL
soliket-0.3.1.dist-info/licenses/LICENSE
soliket-0.3.1.dist-info/RECORD
