Metadata-Version: 2.4
Name: soliket
Version: 0.3.1
Summary: Likelihood and Theory codes for the Simons Observatory.
Project-URL: Homepage, https://github.com/simonsobs/SOLikeT/
Project-URL: Documentation, https://soliket.readthedocs.io/en/latest/
Author: Simons Observatory
License: MIT
License-File: LICENSE
Requires-Python: <3.14,>3.9
Requires-Dist: astropy>=5.3.4
Requires-Dist: camb>=1.5
Requires-Dist: cobaya>=3.5.5
Requires-Dist: getdist>=1.3.1
Requires-Dist: numpy>=1.22.1; python_version < '3.12'
Requires-Dist: numpy>=1.25; python_version >= '3.12'
Requires-Dist: pandas<2.1.0; python_version >= '3.12' and python_version < '3.13'
Requires-Dist: requests>=2.18
Requires-Dist: sacc>=0.9
Requires-Dist: scipy>=1.10.0
Provides-Extra: all
Requires-Dist: cosmopower>=0.2.0; (python_version < '3.12' and sys_platform != 'win32') and extra == 'all'
Requires-Dist: fgspectra>=1.3.0; (python_version < '3.13') and extra == 'all'
Requires-Dist: mflike>=1.0.1; (python_version < '3.13') and extra == 'all'
Requires-Dist: pyccl>=3.1.2; (sys_platform != 'win32' and python_version < '3.13') and extra == 'all'
Requires-Dist: pyhalomodel>=1.0.1; (python_version < '3.13') and extra == 'all'
Requires-Dist: syslibrary>=0.2.0; (python_version < '3.13') and extra == 'all'
Requires-Dist: tensorflow-probability>=0.20.1; (python_version < '3.12' and sys_platform != 'win32') and extra == 'all'
Requires-Dist: tensorflow>=2.12; (python_version < '3.12' and sys_platform != 'win32') and extra == 'all'
Provides-Extra: dev
Requires-Dist: pre-commit; extra == 'dev'
Requires-Dist: pytest-cov; extra == 'dev'
Requires-Dist: pytest>=6.2.5; extra == 'dev'
Requires-Dist: ruff; extra == 'dev'
Requires-Dist: scikit-learn>=1.2; extra == 'dev'
Provides-Extra: docs
Requires-Dist: sphinx; extra == 'docs'
Requires-Dist: sphinx-rtd-theme; extra == 'docs'
Provides-Extra: emulator
Requires-Dist: cosmopower>=0.2.0; (python_version < '3.12' and sys_platform != 'win32') and extra == 'emulator'
Requires-Dist: tensorflow-probability>=0.20.1; (python_version < '3.12' and sys_platform != 'win32') and extra == 'emulator'
Requires-Dist: tensorflow>=2.12; (python_version < '3.12' and sys_platform != 'win32') and extra == 'emulator'
Provides-Extra: jupyter
Requires-Dist: jupyter>=1.1.1; extra == 'jupyter'
Provides-Extra: mflike
Requires-Dist: fgspectra>=1.3.0; (python_version < '3.13') and extra == 'mflike'
Requires-Dist: mflike>=1.0.1; (python_version < '3.13') and extra == 'mflike'
Requires-Dist: syslibrary>=0.2.0; (python_version < '3.13') and extra == 'mflike'
Provides-Extra: pyccl
Requires-Dist: pyccl>=3.1.2; (sys_platform != 'win32' and python_version < '3.13') and extra == 'pyccl'
Provides-Extra: pyhalomodel
Requires-Dist: pyhalomodel>=1.0.1; (python_version < '3.13') and extra == 'pyhalomodel'
